CHANGELOG
COPYING
MANIFEST.in
README.md
setup.py
PyBluez_updated.egg-info/PKG-INFO
PyBluez_updated.egg-info/SOURCES.txt
PyBluez_updated.egg-info/dependency_links.txt
PyBluez_updated.egg-info/eager_resources.txt
PyBluez_updated.egg-info/requires.txt
PyBluez_updated.egg-info/top_level.txt
PyBluez_updated.egg-info/zip-safe
bluetooth/__init__.py
bluetooth/ble.py
bluetooth/bluez.py
bluetooth/btcommon.py
bluetooth/macos.py
bluetooth/msbt.py
bluez/btmodule.c
bluez/btmodule.h
bluez/btsdp.c
bluez/btsdp.h
bluez/pythoncapi_compat.h
examples/advanced/inquiry-with-rssi.py
examples/advanced/l2-mtu.py
examples/advanced/l2-unreliable-client.py
examples/advanced/l2-unreliable-server.py
examples/advanced/read-local-bdaddr.py
examples/advanced/write-inquiry-scan.py
examples/ble/beacon.py
examples/ble/beacon_scan.py
examples/ble/read_name.py
examples/ble/scan.py
examples/bluezchat/bluezchat.py
examples/simple/asynchronous-inquiry.py
examples/simple/inquiry.py
examples/simple/l2capclient.py
examples/simple/l2capserver.py
examples/simple/rfcomm-client.py
examples/simple/rfcomm-server.py
examples/simple/sdp-browse.py
macos/LightAquaBlue/BBBluetoothChannelDelegate.h
macos/LightAquaBlue/BBBluetoothOBEXClient.h
macos/LightAquaBlue/BBBluetoothOBEXServer.h
macos/LightAquaBlue/BBLocalDevice.h
macos/LightAquaBlue/BBMutableOBEXHeaderSet.h
macos/LightAquaBlue/BBOBEXHeaderSet.h
macos/LightAquaBlue/BBOBEXRequest.h
macos/LightAquaBlue/BBOBEXRequestHandler.h
macos/LightAquaBlue/BBOBEXResponse.h
macos/LightAquaBlue/BBServiceAdvertiser.h
macos/LightAquaBlue/BBStreamingInputStream.h
macos/LightAquaBlue/BBStreamingOutputStream.h
macos/LightAquaBlue/LightAquaBlue.h
msbt/_msbt.c